LICENSE
MANIFEST.in
README.md
setup.py
pocket_cli/__init__.py
pocket_cli/app.py
pocket_cli/cli.py
pocket_cli/config.py
pocket_cli/exceptions.py
pocket_cli/storage.py
pocket_cli/utils.py
pocket_cli.egg-info/PKG-INFO
pocket_cli.egg-info/SOURCES.txt
pocket_cli.egg-info/dependency_links.txt
pocket_cli.egg-info/entry_points.txt
pocket_cli.egg-info/requires.txt
pocket_cli.egg-info/top_level.txt