Metadata-Version: 1.0
Name: pocket-cli
Version: 0.1.4
Summary: A terminal application for Pocket
Home-page: https://github.com/rakanalh/pocket-api
Author: Rakan Alhneiti
Author-email: rakan.alhneiti@gmail.com
License: LICENSE
Platform: UNKNOWN
